villaAuthSdk/__init__.py
villaAuthSdk/_nbdev.py
villaAuthSdk/auth.py
villaAuthSdk-0.0.12.dist-info/LICENSE
villaAuthSdk-0.0.12.dist-info/METADATA
villaAuthSdk-0.0.12.dist-info/WHEEL
villaAuthSdk-0.0.12.dist-info/entry_points.txt
villaAuthSdk-0.0.12.dist-info/top_level.txt
villaAuthSdk-0.0.12.dist-info/RECORD
